shellutil/__init__.py
shellutil-0.6.dist-info/METADATA
shellutil-0.6.dist-info/WHEEL
shellutil-0.6.dist-info/top_level.txt
shellutil-0.6.dist-info/RECORD
